mercurial_extension_helloworld-0.1.dist-info/RECORD
mercurial_extension_helloworld-0.1.dist-info/metadata.json
mercurial_extension_helloworld-0.1.dist-info/top_level.txt
mercurial_extension_helloworld-0.1.dist-info/WHEEL
mercurial_extension_helloworld-0.1.dist-info/METADATA
mercurial_extension_helloworld-0.1.dist-info/DESCRIPTION.rst
hgext/helloworld.py
hgext/__init__.py
