Metadata-Version: 2.0
Name: mercurial-extension-helloworld
Version: 0.1
Summary: Helloworld extension for Mercurial
Home-page: https://github.com/tokibito/mercurial-helloworld
Author: Shinya Okano
Author-email: tokibito@gmail.com
License: UNKNOWN
Platform: UNKNOWN
Classifier: Programming Language :: Python :: 2.7
Classifier: License :: OSI Approved :: MIT License
Requires-Dist: Mercurial
